operacoes.py
operacoes-1.0.0.dist-info/METADATA
operacoes-1.0.0.dist-info/WHEEL
operacoes-1.0.0.dist-info/top_level.txt
operacoes-1.0.0.dist-info/RECORD
