Metadata-Version: 2.1
Name: operacoes
Version: 1.0.0
Summary: As quatro principais operações matemáticas
Home-page: UNKNOWN
Author: Lucas Emanual Nascimento Nóbrega Dias
Author-email: lucasiamtr@gmail.com
License: UNKNOWN
Platform: UNKNOWN
